arthur_bench/__init__.py
arthur_bench/version.py
arthur_bench/client/__init__.py
arthur_bench/client/bench_client.py
arthur_bench/client/utils.py
arthur_bench/client/auth/__init__.py
arthur_bench/client/auth/helpers.py
arthur_bench/client/auth/refresh.py
arthur_bench/client/http/__init__.py
arthur_bench/client/http/helper.py
arthur_bench/client/http/requests.py
arthur_bench/client/http/validation.py
arthur_bench/client/local/__init__.py
arthur_bench/client/local/client.py
arthur_bench/client/rest/__init__.py
arthur_bench/client/rest/client.py
arthur_bench/client/rest/admin/__init__.py
arthur_bench/client/rest/admin/client.py
arthur_bench/client/rest/admin/models.py
arthur_bench/client/rest/bench/__init__.py
arthur_bench/client/rest/bench/client.py
arthur_bench/exceptions/__init__.py
arthur_bench/exceptions/exceptions.py
arthur_bench/logger/__init__.py
arthur_bench/logger/logger.py
arthur_bench/models/__init__.py
arthur_bench/models/client.py
arthur_bench/models/models.py
arthur_bench/models/scoring.py
arthur_bench/run/__init__.py
arthur_bench/run/testrun.py
arthur_bench/run/testsuite.py
arthur_bench/run/utils.py
arthur_bench/scoring/__init__.py
arthur_bench/scoring/bertscore.py
arthur_bench/scoring/exact_match.py
arthur_bench/scoring/hallucination.py
arthur_bench/scoring/hedging_language.py
arthur_bench/scoring/python_unit_testing.py
arthur_bench/scoring/qa_quality.py
arthur_bench/scoring/readability.py
arthur_bench/scoring/scorer.py
arthur_bench/scoring/specificity.py
arthur_bench/scoring/summary_quality.py
arthur_bench/scoring/utils.py
arthur_bench/scoring/word_count_match.py
arthur_bench/scoring/prompts/qa_correctness.py
arthur_bench/scoring/prompts/summary_quality.py
arthur_bench/server/__init__.py
arthur_bench/server/run_server.py
arthur_bench/server/spa_static_files.py
arthur_bench/server/js/dist/arthur-triangle-favicon.png
arthur_bench/server/js/dist/bundle.js
arthur_bench/server/js/dist/bundle.js.LICENSE.txt
arthur_bench/server/js/dist/bundle.js.map
arthur_bench-0.3.1.dist-info/LICENSE
arthur_bench-0.3.1.dist-info/METADATA
arthur_bench-0.3.1.dist-info/WHEEL
arthur_bench-0.3.1.dist-info/entry_points.txt
arthur_bench-0.3.1.dist-info/top_level.txt
arthur_bench-0.3.1.dist-info/RECORD
