Metadata-Version: 2.1
Name: arthur_bench
Version: 0.3.1
Summary: validate models for production
Author-email: ArthurAI <info@arthur.ai>
License: MIT
Project-URL: Homepage, https://www.arthur.ai/arthur-bench
Project-URL: Documentation, https://bench.readthedocs.io/
Project-URL: Repository, https://github.com/arthur-ai/bench
Classifier: Development Status :: 5 - Production/Stable
Classifier: Programming Language :: Python :: 3.9
Classifier: Programming Language :: Python :: 3.10
Classifier: Programming Language :: Python :: 3.11
License-File: LICENSE
Requires-Dist: evaluate ~=0.4.0
Requires-Dist: openai ~=0.27
Requires-Dist: pandas ~=2.0.1
Requires-Dist: langchain ~=0.0.170
Requires-Dist: sentencepiece ==0.1.99
Requires-Dist: bert-score ~=0.3
Requires-Dist: nltk ~=3.8
Requires-Dist: tqdm ~=4.65
Requires-Dist: pydantic <2.0,>=1.10.0
Requires-Dist: pyjwt <3,>=2.6
Requires-Dist: requests ~=2.28
Requires-Dist: requests-toolbelt ~=1.0
Requires-Dist: textstat ~=0.7
Requires-Dist: tiktoken ~=0.4
Requires-Dist: transformers ==4.29.2
Requires-Dist: wordfreq ~=3.0
Provides-Extra: docs
Requires-Dist: sphinx ; extra == 'docs'
Requires-Dist: furo ; extra == 'docs'
Requires-Dist: myst-parser ; extra == 'docs'
Provides-Extra: server
Requires-Dist: fastapi ~=0.99.1 ; extra == 'server'
Requires-Dist: uvicorn ~=0.22.0 ; extra == 'server'
Requires-Dist: amplitude-analytics ==1.1.1 ; extra == 'server'
